<?xml version="1.0"?>
<opencv_storage>
<stage12>
  <maxWeakCount>100</maxWeakCount>
  <stageThreshold>-1.9022810459136963e+00</stageThreshold>
  <weakClassifiers>
    <_>
      <internalNodes>
        0 -1 21 -583928560 -33686027 -33554443 -33686051 -75 -257
        -1182251 -573711907</internalNodes>
      <leafValues>
        -4.6197128295898438e-01 4.1379738599061966e-02</leafValues></_>
    <_>
      <internalNodes>
        0 -1 873 -1 -33554433 -1 233832447 -528387 816952741 -28692
        218483852</internalNodes>
      <leafValues>
        -2.6194074749946594e-01 1.9936344027519226e-01</leafValues></_>
    <_>
      <internalNodes>
        0 -1 1000 184222975 -61441 -1561165825 -20481 -1310721 -4097
        -1115137 -65</internalNodes>
      <leafValues>
        -1.9040714204311371e-01 2.1044860780239105e-01</leafValues></_>
    <_>
      <internalNodes>
        0 -1 770 -4561 -1023418369 -285241818 -855642129 -210275273
        -159943337 -76027130 -210502353</internalNodes>
      <leafValues>
        -1.6984494030475616e-01 2.3491238057613373e-01</leafValues></_>
    <_>
      <internalNodes>
        0 -1 135 -96804865 2052775935 -4456769 738197503 -2005365539
        -84254721 -1414492482 577990267</internalNodes>
      <leafValues>
        -2.2987246513366699e-01 1.5506020188331604e-01</leafValues></_>
    <_>
      <internalNodes>
        0 -1 973 -524425 -9373833 -8455361 -46991374 -8946064 -13437580
        -30250476 -14483662</internalNodes>
      <leafValues>
        -1.4360435307025909e-01 2.1858699619770050e-01</leafValues></_>
    <_>
      <internalNodes>
        0 -1 116 -553713924 -553648145 -1424167300 -1075867889
        -1997503272 -924299868 -1997494104 191579911</internalNodes>
      <leafValues>
        -2.3453640937805176e-01 9.4515815377235413e-02</leafValues></_>
    <_>
      <internalNodes>
        0 -1 165 -2269 13106175 -167780521 -168298497 -2117 32691827
        -547357185 1476392959</internalNodes>
      <leafValues>
        -1.9618074595928192e-01 1.3824971020221710e-01</leafValues></_>
    <_>
      <internalNodes>
        0 -1 996 254533041 -1078788176 -526851 -131587 1060894205
        -1074792451 536837631 1073681779</internalNodes>
      <leafValues>
        -1.7765592038631439e-01 1.4133648574352264e-01</leafValues></_>
    <_>
      <internalNodes>
        0 -1 656 1146364788 -1347141697 1067401215 -1346420801
        -285271235 -34177 -57505 -1342232049</internalNodes>
      <leafValues>
        -2.1003817021846771e-01 1.0068189352750778e-01</leafValues></_>
    <_>
      <internalNodes>
        0 -1 75 -16781313 -1902474598 -6213 721292476 -870257412
        -2003271468 -126821292 2116688</internalNodes>
      <leafValues>
        -3.0828428268432617e-01 8.0070652067661285e-02</leafValues></_>
    <_>
      <internalNodes>
        0 -1 1010 15859967 1627336703 1256898527 546717695 -730705730
        2004303685 -136905729 -229457921</internalNodes>
      <leafValues>
        -2.1154962480068207e-01 1.0606408864259720e-01</leafValues></_>
    <_>
      <internalNodes>
        0 -1 21 583940001 1379014520 363165053 -570451178 355473258
        -2048197164 355866426 1293312288</internalNodes>
      <leafValues>
        -1.9451142847537994e-01 1.1261963099241257e-01</leafValues></_>
    <_>
      <internalNodes>
        0 -1 326 -436215390 13034982 -140260096 -978580052 -1074362385
        15778279 2138556367 1441032182</internalNodes>
      <leafValues>
        -2.4541315436363220e-01 8.6378566920757294e-02</leafValues></_>
    <_>
      <internalNodes>
        0 -1 150 -495784078 -202231809 -537649185 1072836479 2119503860
        -8647169 -2355320 1334052097</internalNodes>
      <leafValues>
        -1.7424446344375610e-01 1.1953321099281311e-01</leafValues></_>
    <_>
      <internalNodes>
        0 -1 0 1052976 938547376 2113762677 -541090571 -1141828163
        -1078001741 1002386943 -25121</internalNodes>
      <leafValues>
        -2.2179557383060455e-01 9.6717022359371185e-02</leafValues></_>
    <_>
      <internalNodes>
        0 -1 350 -1145067741 -923881478 -138451695 -47412 -1358240841
        -1941769246 863499639 -976230949</internalNodes>
      <leafValues>
        -1.3593524694442749e-01 1.4376127719879150e-01</leafValues></_>
    <_>
      <internalNodes>
        0 -1 427 1785888624 -2179073 2147172351 1065238399 1030041969
        -1073889413 -245767 -1894973431</internalNodes>
      <leafValues>
        -1.5640461444854736e-01 1.2453164905309677e-01</leafValues></_>
    <_>
      <internalNodes>
        0 -1 856 -487078257 -603983875 782692335 233793503 -11059451
        -1116209819 -11038833 -1919947827</internalNodes>
      <leafValues>
        -1.0937611013650894e-01 1.8154607713222504e-01</leafValues></_>
    <_>
      <internalNodes>
        0 -1 156 -84162817 2147441663 -92602626 2119859935 1584875590
        -26255586 -27272994 -83886081</internalNodes>
      <leafValues>
        -9.3994595110416412e-02 2.0798344910144806e-01</leafValues></_>
    <_>
      <internalNodes>
        0 -1 801 -261038732 823195028 1878994738 1039924987 -1155805195
        968017381 255790889 219097099</internalNodes>
      <leafValues>
        -1.6769926249980927e-01 1.1091915518045425e-01</leafValues></_>
    <_>
      <internalNodes>
        0 -1 437 -361083137 2136882939 -65537 469377023 -44169642
        -17150119 -2457857 -1355141573</internalNodes>
      <leafValues>
        -1.2904302775859833e-01 1.3827310502529144e-01</leafValues></_>
    <_>
      <internalNodes>
        0 -1 960 -365804938 -1040512257 716320351 44699391 -83152128
        2105177663 -72175953 -321</internalNodes>
      <leafValues>
        -1.6980092227458954e-01 1.0393975675106049e-01</leafValues></_>
    <_>
      <internalNodes>
        0 -1 12 1617421966 -235608385 803399436 -24320050 341120767
        -185088273 2134374155 1456963343</internalNodes>
      <leafValues>
        -1.5046408772468567e-01 1.1432591080665588e-01</leafValues></_>
    <_>
      <internalNodes>
        0 -1 836 676346996 -1076184579 1065254908 -1075986699
        -1342324739 -270745635 -1077993473 -1346491848</internalNodes>
      <leafValues>
        -1.8877670168876648e-01 9.0543739497661591e-02</leafValues></_>
    <_>
      <internalNodes>
        0 -1 814 -537069836 -131064524 1341525811 -1918027971 -1146891
        -1141662539 254676833 224862231</internalNodes>
      <leafValues>
        -1.6887854039669037e-01 1.0079088062047958e-01</leafValues></_>
    <_>
      <internalNodes>
        0 -1 873 1088930348 1408616349 -1880166472 -223171574 1431144070
        -378908815 -2062226277 -224741609</internalNodes>
      <leafValues>
        -1.0744190216064453e-01 1.6044077277183533e-01</leafValues></_>
    <_>
      <internalNodes>
        0 -1 1030 -12847824 -576708560 -11382281 -863482508 993263586
        -1348428556 2133737466 212817143</internalNodes>
      <leafValues>
        -1.6764822602272034e-01 1.0658882558345795e-01</leafValues></_>
    <_>
      <internalNodes>
        0 -1 685 -1105 -104863777 -353448532 -84936193 1686075007
        1344238596 -604242296 -244318497</internalNodes>
      <leafValues>
        -1.3431800901889801e-01 1.2276651710271835e-01</leafValues></_>
    <_>
      <internalNodes>
        0 -1 298 2013262846 1149020991 1004340095 -810636609 2009972725
        2111081412 -62579 713886219</internalNodes>
      <leafValues>
        -1.2847265601158142e-01 1.3052152097225189e-01</leafValues></_>
    <_>
      <internalNodes>
        0 -1 57 1008972080 -638810738 -6815745 1607458780 550548724
        917638588 2111165948 -850403939</internalNodes>
      <leafValues>
        -1.3973002135753632e-01 1.1736258119344711e-01</leafValues></_>
    <_>
      <internalNodes>
        0 -1 45 1416095520 1155458983 2105159198 -844191826 -38537281
        1962325759 2138566431 -587182326</internalNodes>
      <leafValues>
        -1.4285376667976379e-01 1.1763675510883331e-01</leafValues></_>
    <_>
      <internalNodes>
        0 -1 919 -566233295 101448487 -1896891728 -1380143574 805303729
        268433283 218039601 212808763</internalNodes>
      <leafValues>
        -1.6198603808879852e-01 9.7377046942710876e-02</leafValues></_>
    <_>
      <internalNodes>
        0 -1 455 -1317275725 -1058033153 1609000723 -33568852
        -1308183115 -2010579498 390558515 -975178289</internalNodes>
      <leafValues>
        -1.0988209396600723e-01 1.4709685742855072e-01</leafValues></_>
    <_>
      <internalNodes>
        0 -1 509 243148644 -386252930 263995228 1064844888 736460213
        -1931313919 1577008313 259072570</internalNodes>
      <leafValues>
        -1.7687058448791504e-01 8.6999565362930298e-02</leafValues></_>
    <_>
      <internalNodes>
        0 -1 349 -349196529 -182059457 -346558657 -419496209 -983185573
        -789054465 -524431 -319343789</internalNodes>
      <leafValues>
        -9.6847489476203918e-02 1.6414204239845276e-01</leafValues></_>
    <_>
      <internalNodes>
        0 -1 1018 1694435487 1352369245 -151584802 1350238175 -992047996
        808789268 -197188 -262996165</internalNodes>
      <leafValues>
        -1.3604754209518433e-01 1.1315754801034927e-01</leafValues></_>
    <_>
      <internalNodes>
        0 -1 255 -696217872 -536937187 781945361 -822345973 -523186180
        -47168003 -402685957 726092555</internalNodes>
      <leafValues>
        -1.2792485952377319e-01 1.1943133920431137e-01</leafValues></_>
    <_>
      <internalNodes>
        0 -1 435 -286065806 -8643593 -4243585 1004478327 -69263052
        -1115719169 -269140167 -1343288792</internalNodes>
      <leafValues>
        -1.0939552634954453e-01 1.3529178500175476e-01</leafValues></_>
    <_>
      <internalNodes>
        0 -1 486 -1342296282 -1023799499 -41943065 -168238021
        -1342193803 -2039449742 -1082196481 1164779578</internalNodes>
      <leafValues>
        -1.4294250309467316e-01 1.0329887270927429e-01</leafValues></_>
    <_>
      <internalNodes>
        0 -1 918 205263920 -1363403279 -1946206723 -1397211523 251608509
        -1423966283 1073625085 -1371927504</internalNodes>
      <leafValues>
        -2.3224124312400818e-01 6.1985787004232407e-02</leafValues></_>
    <_>
      <internalNodes>
        0 -1 680 -67391765 10652497 1864804994 -328949556 2054254965
        993144343 -2073568 -548146797</internalNodes>
      <leafValues>
        -1.6223788261413574e-01 8.8760025799274445e-02</leafValues></_>
    <_>
      <internalNodes>
        0 -1 175 -286347776 -1073744129 787426867 -137217 -1209024521
        -1873931561 -195035337 1436517</internalNodes>
      <leafValues>
        -1.6196896135807037e-01 9.5227159559726715e-02</leafValues></_>
    <_>
      <internalNodes>
        0 -1 1022 -16806392 1057280 1711456020 1346689374 -1125675744
        142083332 -1091376952 -805241250</internalNodes>
      <leafValues>
        -1.8767990171909332e-01 7.7173165977001190e-02</leafValues></_>
    <_>
      <internalNodes>
        0 -1 914 -929516300 -17004580 -597852195 -604047397 536788476
        -2441256 1071595519 -1079366626</internalNodes>
      <leafValues>
        -1.0913597047328949e-01 1.3252110779285431e-01</leafValues></_>
    <_>
      <internalNodes>
        0 -1 832 -588261899 -1630228898 805273565 -1145520737
        -1073761291 -1375746049 260915197 -1464128485</internalNodes>
      <leafValues>
        -9.3546055257320404e-02 1.6030021011829376e-01</leafValues></_>
    <_>
      <internalNodes>
        0 -1 20 271594768 78156912 502012917 -571524963 917452049
        -1678009862 927405367 -1647340291</internalNodes>
      <leafValues>
        -2.3648945987224579e-01 6.2913790345191956e-02</leafValues></_>
    <_>
      <internalNodes>
        0 -1 413 -486666625 -1150678162 2146861053 2147360316
        -1909318347 -1342546116 -245055499 -1947598768</internalNodes>
      <leafValues>
        -1.3785548508167267e-01 1.0387390851974487e-01</leafValues></_>
    <_>
      <internalNodes>
        0 -1 925 -1059642226 -620798739 -1963856210 3102719 -96999680
        -260934572 -76038264 -78512673</internalNodes>
      <leafValues>
        -1.3085751235485077e-01 1.0668895393610001e-01</leafValues></_>
    <_>
      <internalNodes>
        0 -1 112 -823221269 -286643400 -302650020 -76798534 170329394
        -1945469072 1164211700 -580397740</internalNodes>
      <leafValues>
        -1.4573144912719727e-01 9.4407543540000916e-02</leafValues></_>
    <_>
      <internalNodes>
        0 -1 713 -441793428 -34153291 -809619649 -536932737 592699381
        892785969 165088939 205982267</internalNodes>
      <leafValues>
        -1.2651705741882324e-01 1.1010981351137161e-01</leafValues></_>
    <_>
      <internalNodes>
        0 -1 216 119515059 -823473774 -680034441 -196297224 105294751
        -894795862 1967650702 -856697396</internalNodes>
      <leafValues>
        -9.8020136356353760e-02 1.4587256312370300e-01</leafValues></_>
    <_>
      <internalNodes>
        0 -1 109 1996484590 753598350 1861172318 728690222 1986359108
        1425304112 1875869450 1078215238</internalNodes>
      <leafValues>
        -2.4202451109886169e-01 5.6212816387414932e-02</leafValues></_>
    <_>
      <internalNodes>
        0 -1 196 926208 15003374 240023388 183435006 1901409552
        -1245416756 2135375684 751664968</internalNodes>
      <leafValues>
        -2.7469447255134583e-01 4.9101151525974274e-02</leafValues></_>
    <_>
      <internalNodes>
        0 -1 160 773362992 -2071458168 -1355015855 -39904808 -1986079567
        -891490373 87232788 -536877154</internalNodes>
      <leafValues>
        -1.7890872061252594e-01 7.6844766736030579e-02</leafValues></_>
    <_>
      <internalNodes>
        0 -1 152 -889565457 2068458043 -318841098 2054319998 1129251908
        -297503152 -991625644 -72194960</internalNodes>
      <leafValues>
        -1.3733549416065216e-01 9.8139435052871704e-02</leafValues></_>
    <_>
      <internalNodes>
        0 -1 865 -1058618194 1442777022 -282923138 220986666 590852029
        834082229 -268464213 17141512</internalNodes>
      <leafValues>
        -1.4467065036296844e-01 9.3686722218990326e-02</leafValues></_>
    <_>
      <internalNodes>
        0 -1 995 241667376 178398804 -542376451 982285948 536845228
        -1073840132 536622332 -1979174632</internalNodes>
      <leafValues>
        -1.7357942461967468e-01 7.5793080031871796e-02</leafValues></_>
    <_>
      <internalNodes>
        0 -1 1025 -20977128 439485964 -1909302817 -797508129 -1143240684
        138085380 -269226248 -267195137</internalNodes>
      <leafValues>
        -1.3177339732646942e-01 1.0204424709081650e-01</leafValues></_>
    <_>
      <internalNodes>
        0 -1 758 -25378956 -1078182402 -4751361 1071267839 -7390283
        -1078166019 -1073791011 -1342558670</internalNodes>
      <leafValues>
        -1.1501580476760864e-01 1.1802135407924652e-01</leafValues></_>
    <_>
      <internalNodes>
        0 -1 9 -782898315 -872108500 1291830800 -821530840 1154858487
        -1997144165 -789482028 89458720</internalNodes>
      <leafValues>
        -1.9585342705249786e-01 6.6744863986968994e-02</leafValues></_>
    <_>
      <internalNodes>
        0 -1 494 1856643362 -1997008912 -1079567589 -547545798 704897957
        -1364183625 1058531229 -1917123413</internalNodes>
      <leafValues>
        -1.1082810163497925e-01 1.2730436027050018e-01</leafValues></_>
    <_>
      <internalNodes>
        0 -1 973 2070575024 -260572240 -1476658497 -86747587 -269697227
        -574800517 -1611157193 -1999829795</internalNodes>
      <leafValues>
        -1.1733703315258026e-01 1.1204837262630463e-01</leafValues></_>
    <_>
      <internalNodes>
        0 -1 841 -218387793 -924912153 -1361400177 -928846369 -10768543
        -8685708 -284113 -103301985</internalNodes>
      <leafValues>
        -8.2811005413532257e-02 1.5817809104919434e-01</leafValues></_>
    <_>
      <internalNodes>
        0 -1 586 1923348936 296615340 218878788 -1716584466 1897226628
        834141621 -706355508 610384556</internalNodes>
      <leafValues>
        -1.8094038963317871e-01 7.3519825935363770e-02</leafValues></_>
    <_>
      <internalNodes>
        0 -1 1031 -1811944432 -1686883235 -633413772 943773148
        -1080451024 -1393019052 -1363231048 -2010057462</internalNodes>
      <leafValues>
        -1.5059857070446014e-01 8.6317427456378937e-02</leafValues></_>
    <_>
      <internalNodes>
        0 -1 959 452867120 -1366378832 -1081109575 -1388694089
        -1909492367 -1896038793 485375908 -1371666384</internalNodes>
      <leafValues>
        -2.0125088095664978e-01 6.5020859241485596e-02</leafValues></_>
    <_>
      <internalNodes>
        0 -1 822 171447488 -67306017 -1229078561 -1243645957 -1703625251
        -6522982 871348730 -1623510897</internalNodes>
      <leafValues>
        -1.0552763938903809e-01 1.2393862009048462e-01</leafValues></_>
    <_>
      <internalNodes>
        0 -1 248 -403789918 -1125506242 1564126708 -381908 688588194
        167910695 1331672540 -838872578</internalNodes>
      <leafValues>
        -9.6268996596336365e-02 1.3525183498859406e-01</leafValues></_>
    <_>
      <internalNodes>
        0 -1 699 -284709084 1947256437 -270553290 -285569281 -180441227
        -180287885 -826346892 -1372307852</internalNodes>
      <leafValues>
        -1.7010177671909332e-01 7.4748307466506958e-02</leafValues></_>
    <_>
      <internalNodes>
        0 -1 1005 2228479 837756382 1721898495 26415031 -521779392
        -243294932 -80544257 -217960769</internalNodes>
      <leafValues>
        -1.5112054347991943e-01 8.3266697824001312e-02</leafValues></_>
    <_>
      <internalNodes>
        0 -1 237 -465662492 -721795153 1879025166 792668715 1358193140
        284312820 2134062869 222497035</internalNodes>
      <leafValues>
        -1.5893602371215820e-01 8.0005928874015808e-02</leafValues></_>
    <_>
      <internalNodes>
        0 -1 662 582882420 -2034622473 -268986625 -1431359617 1870290801
        -1097187970 1811885943 -1359007217</internalNodes>
      <leafValues>
        -1.6255769133567810e-01 7.9165793955326080e-02</leafValues></_>
    <_>
      <internalNodes>
        0 -1 676 -521148368 943106613 -1947260929 -1523145089
        -1346506827 928317273 721094777 539599113</internalNodes>
      <leafValues>
        -1.4503961801528931e-01 8.7051995098590851e-02</leafValues></_>
    <_>
      <internalNodes>
        0 -1 934 1614744613 -897620899 -134559106 1354407455 -99209164
        -2008002556 -76486994 -1151175361</internalNodes>
      <leafValues>
        -1.2541644275188446e-01 1.0138367116451263e-01</leafValues></_>
    <_>
      <internalNodes>
        0 -1 140 -390421878 1522144986 -1661278214 2079893238 1114783752
        1849056324 1825856720 -2089720492</internalNodes>
      <leafValues>
        -1.4951673150062561e-01 8.5117891430854797e-02</leafValues></_>
    <_>
      <internalNodes>
        0 -1 308 537528842 992616186 -862552462 976234074 1014513668
        -317165697 190349044 -2006954908</internalNodes>
      <leafValues>
        -2.1970444917678833e-01 5.4250802844762802e-02</leafValues></_>
    <_>
      <internalNodes>
        0 -1 53 -2107428346 12940966 -401976482 787412718 -176851072
        -51279378 -1084795122 785678150</internalNodes>
      <leafValues>
        -1.6860413551330566e-01 7.0639818906784058e-02</leafValues></_>
    <_>
      <internalNodes>
        0 -1 83 -502362358 -822223415 -1350652159 -286392437 -1328153455
        14024701 -201903326 1088368834</internalNodes>
      <leafValues>
        -1.4477851986885071e-01 8.2612045109272003e-02</leafValues></_>
    <_>
      <internalNodes>
        0 -1 278 1257171822 285144863 934759167 790366779 1869893488
        -187667001 -1145102581 -814153141</internalNodes>
      <leafValues>
        -1.0761060565710068e-01 1.1417294293642044e-01</leafValues></_>
    <_>
      <internalNodes>
        0 -1 445 -12597270 54183843 -967908350 1541540842 1475749690
        57145319 1406661202 1476151245</internalNodes>
      <leafValues>
        -1.6909135878086090e-01 7.2838976979255676e-02</leafValues></_>
    <_>
      <internalNodes>
        0 -1 73 1948168484 -790845544 -25296939 -540037714 139998716
        -1132976824 1783979484 1560282376</internalNodes>
      <leafValues>
        -1.8460814654827118e-01 6.3034474849700928e-02</leafValues></_>
    <_>
      <internalNodes>
        0 -1 15 -452989914 318636031 1718077984 1090322301 -545538113
        910628906 -1074790437 1416846966</internalNodes>
      <leafValues>
        -1.6897766292095184e-01 7.1009173989295959e-02</leafValues></_>
    <_>
      <internalNodes>
        0 -1 998 403644688 -2113391712 1593703892 -978543532 516828312
        -1347616844 248190192 -2004872108</internalNodes>
      <leafValues>
        -1.9669246673583984e-01 5.8808155357837677e-02</leafValues></_>
    <_>
      <internalNodes>
        0 -1 618 780069668 -84219906 461061039 -1119930321 -272171723
        -1597610895 1868106153 225904682</internalNodes>
      <leafValues>
        -1.2042281031608582e-01 9.8781019449234009e-02</leafValues></_>
    <_>
      <internalNodes>
        0 -1 303 -633680111 2050711551 -140904835 1054834231 -1170436980
        -889205030 -28112607 -1410130125</internalNodes>
      <leafValues>
        -9.6114724874496460e-02 1.1753463745117188e-01</leafValues></_>
    <_>
      <internalNodes>
        0 -1 1000 0 12061898 538977525 34757839 69206032 448208477
        35655422 595204799</internalNodes>
      <leafValues>
        -4.5231285691261292e-01 2.4999994784593582e-02</leafValues></_>
    <_>
      <internalNodes>
        0 -1 103 715270690 -18201714 -604840194 1526899210 69223490
        1717724487 1094800212 1413922898</internalNodes>
      <leafValues>
        -2.2683311998844147e-01 4.8938602209091187e-02</leafValues></_>
    <_>
      <internalNodes>
        0 -1 232 -309594446 -363721028 -1912736515 -42280462 -186210678
        241306932 1163388895 -989862440</internalNodes>
      <leafValues>
        -8.7236791849136353e-02 1.2980020046234131e-01</leafValues></_>
    <_>
      <internalNodes>
        0 -1 560 -4212813 12315327 1953755138 -859953686 1932776981
        11589394 1450266720 -713163521</internalNodes>
      <leafValues>
        -1.3448882102966309e-01 8.5576884448528290e-02</leafValues></_>
    <_>
      <internalNodes>
        0 -1 988 -549458415 444495709 -222791715 1601754780 -1482314732
        -1414537355 234274044 -551291555</internalNodes>
      <leafValues>
        -8.7286651134490967e-02 1.3090839982032776e-01</leafValues></_>
    <_>
      <internalNodes>
        0 -1 56 822293794 -798425264 1837478241 -715329556 -2022396105
        1185335075 1499951943 -708709292</internalNodes>
      <leafValues>
        -1.5025605261325836e-01 7.3797307908535004e-02</leafValues></_>
    <_>
      <internalNodes>
        0 -1 162 -1999717072 244225454 -1090522827 -1815365098
        -922945794 -1359038213 1431336309 261557778</internalNodes>
      <leafValues>
        -1.5749715268611908e-01 7.2253905236721039e-02</leafValues></_>
    <_>
      <internalNodes>
        0 -1 769 -254696702 1903427511 -319150314 -256711042 -800215243
        -176924905 -569512908 203434042</internalNodes>
      <leafValues>
        -1.7635053396224976e-01 6.5720714628696442e-02</leafValues></_>
    <_>
      <internalNodes>
        0 -1 1014 1255869631 -109244609 2036924338 1897397759 -957239132
        -1811214523 -269616724 -78381121</internalNodes>
      <leafValues>
        -7.0884659886360168e-02 1.6275118291378021e-01</leafValues></_>
    <_>
      <internalNodes>
        0 -1 884 581083396 2084054999 802629919 -35873004 -1089428172
        -1731125737 198192878 -1155071958</internalNodes>
      <leafValues>
        -1.0717321932315826e-01 1.1052330583333969e-01</leafValues></_>
    <_>
      <internalNodes>
        0 -1 316 170002000 978458679 -1675695913 444206692 249039360
        -25273282 -2108399088 -1171121132</internalNodes>
      <leafValues>
        -2.2373868525028229e-01 5.2218042314052582e-02</leafValues></_>
    <_>
      <internalNodes>
        0 -1 421 -230231182 -1073856642 -136364033 1069384767 -71521376
        -271876285 -303100421 -1892742829</internalNodes>
      <leafValues>
        -7.8511223196983337e-02 1.4450512826442719e-01</leafValues></_>
    <_>
      <internalNodes>
        0 -1 107 -265622532 -564199660 -1965849060 1849607941 1890881532
        1882398717 -140572133 21842511</internalNodes>
      <leafValues>
        -1.5026146173477173e-01 8.4203019738197327e-02</leafValues></_>
    <_>
      <internalNodes>
        0 -1 970 1525022853 -656733116 -489492742 13258623 -97090496
        -1707392172 -1150042478 -213658017</internalNodes>
      <leafValues>
        -1.2461978942155838e-01 8.9822806417942047e-02</leafValues></_></weakClassifiers></stage12>
</opencv_storage>
